uot/__init__.py
uot/algorithms/col_gen.py
uot/algorithms/gradient_ascent.py
uot/algorithms/lbfgs.py
uot/algorithms/lp.py
uot/algorithms/pdgd.py
uot/algorithms/sinkhorn.py
uot/algorithms/utils.py
uot/color_transfer/color_transfer.py
uot/core/__init__.py
uot/core/analysis.py
uot/core/dataset.py
uot/core/experiment.py
uot/core/suites.py
uot/experiments/plotter.py
uot/experiments/time_precision_experiments.py
uot/mnist_classification/count_pairwise_distances.py
uot/mnist_classification/mnist_classification.py
uot/test/playground.py
uot-0.1.15.dist-info/METADATA
uot-0.1.15.dist-info/WHEEL
uot-0.1.15.dist-info/top_level.txt
uot-0.1.15.dist-info/RECORD
